hwsoftmcp_weikb/__init__.py
hwsoftmcp_weikb/main.py
hwsoftmcp_weikb-0.1.8.dist-info/METADATA
hwsoftmcp_weikb-0.1.8.dist-info/WHEEL
hwsoftmcp_weikb-0.1.8.dist-info/entry_points.txt
hwsoftmcp_weikb-0.1.8.dist-info/top_level.txt
hwsoftmcp_weikb-0.1.8.dist-info/RECORD
