Metadata-Version: 2.4
Name: hwsoftmcp_weikb
Version: 0.1.8
Summary: A toolkit for MCP operations
Requires-Python: >=3.10
Requires-Dist: mcp[cli]>=1.6.0
